CHANGES.txt
LICENSE.txt
MANIFEST.in
README.rst
req.txt
req_test.txt
setup.py
python_vdx.egg-info/PKG-INFO
python_vdx.egg-info/SOURCES.txt
python_vdx.egg-info/dependency_links.txt
python_vdx.egg-info/requires.txt
python_vdx.egg-info/top_level.txt
vdx/__init__.py
vdx/diagramm.py
vdx/shapes.py
vdx/shapes/AND.xml
vdx/shapes/Component.xml
vdx/shapes/Connects.xml
vdx/shapes/DinamicConnection.xml
vdx/shapes/EnterpriseArea.xml
vdx/shapes/Event.xml
vdx/shapes/Function.xml
vdx/shapes/InformationMaterial.xml
vdx/shapes/MainProcess.xml
vdx/shapes/OR.xml
vdx/shapes/OrganizationalUnit.xml
vdx/shapes/ProcessGroup.xml
vdx/shapes/ProcessPath.xml
vdx/shapes/XOR.xml
vdx/shapes/diagramm_body.xml