Metadata-Version: 1.1
Name: python-vdx
Version: 0.1
Summary: Package for working with MS Visio VDX files
Home-page: http://gitlab.stratatech.ru/public/projects/python_vdx/python_vdx
Author: Strata Tech Ltd. ( http://stratatech.ru )
Author-email: info@stratatech.ru
License: LICENSE.txt
Platform: UNKNOWN
Classifier: Development Status :: 4 - Beta
Classifier: Intended Audience :: Developers
Classifier: License :: OSI Approved :: GNU General Public License v3 (GPLv3)
Classifier: Natural Language :: English
Classifier: Natural Language :: Russian
Classifier: Programming Language :: Python
Classifier: Programming Language :: Python :: 2
Classifier: Programming Language :: Python :: 2.7
Classifier: Topic :: Software Development :: Libraries :: Python Modules
